harder/__init__.py
harder/gym.py
harder/policy.py
harder/q.py
harder-0.0.6.dist-info/METADATA
harder-0.0.6.dist-info/RECORD
harder-0.0.6.dist-info/WHEEL
harder-0.0.6.dist-info/top_level.txt
